transutil/__init__.py
transutil/__version__.py
transutil/config.py
transutil/crypter.py
transutil/datastructures.py
transutil/eid.py
transutil/http_status.py
transutil/mailer.py
transutil/module_loading.py
transutil/py.typed
transutil/sanitizer.py
transutil/chiper/__init__.py
transutil/chiper/axi.py
transutil/chiper/base.py
transutil/chiper/chipbase.py
transutil/chiper/encoder.py
transutil/chiper/exception.py
transutil/chiper/types.py
transutil/dispatcher/__init__.py
transutil/dispatcher/callbacklist.py
transutil/dispatcher/eventdispatcher.py
transutil/dispatcher/eventqueue.py
transutil/dispatcher/lock.py
transutil/dispatcher/policy.py
transutil/dispatcher/internal/__init__.py
transutil/dispatcher/internal/linkedlist.py
transutil/dispatcher/internal/lockguard.py
transutil/http/__init__.py
transutil/http/client.py
transutil/http/response.py
transutil/syncbit/__init__.py
transutil/syncbit/configs.py
transutil/syncbit/contexts.py
transutil/syncbit/exceptions.py
transutil/syncbit/schema.py
transutil/syncbit/type_validation.py
transutil/syncbit/utils.py
transutil/syncbit/validate.py
transutil/syncbit/fields/__init__.py
transutil/syncbit/fields/base.py
transutil/syncbit/fields/nesting.py
transutil/syncbit/fields/primitive.py
transutil/syncbit/fields/structs.py
transutil/syncbit/fields/typings.py
transutil/typedclasses/__init__.py
transutil/typedclasses/core.py
transutil/validator/__init__.py
transutil/validator/_fields.py
transutil/validator/exceptions.py
transutil/validator/fields.py
transutil/validator/schema.py
transutil-1.0.1.dist-info/LICENSE
transutil-1.0.1.dist-info/METADATA
transutil-1.0.1.dist-info/WHEEL
transutil-1.0.1.dist-info/top_level.txt
transutil-1.0.1.dist-info/RECORD
