Metadata-Version: 2.1
Name: transutil
Version: 1.0.1
Summary: Introducing Transutil, the ultimate productivity utility tool designed to streamline your workflow. Packed with an array of powerful features, Transutil offers a seamless experience like no other. Enjoy a secure and efficient workflow with our built-in chiper, providing a robust alternative to JWT.
Home-page: https://github.com/embrake/aquilify/
Author: Pawan kumar
Author-email: embrakeproject@gmail.com
License: BSD-3-Clause
Keywords: tool-box,Python utils,user-friendly,high-level,ASGI,backend
Classifier: Development Status :: 5 - Production/Stable
Classifier: Framework :: AsyncIO
Classifier: Intended Audience :: Developers
Classifier: Topic :: Internet :: WWW/HTTP :: HTTP Servers
Classifier: License :: OSI Approved :: BSD License
Classifier: Programming Language :: Python :: 3
Classifier: Programming Language :: Python :: 3.6
Classifier: Programming Language :: Python :: 3.7
Classifier: Programming Language :: Python :: 3.8
Classifier: Programming Language :: Python :: 3.9
License-File: LICENSE
